tests/__init__.py
uniqcharstest3-1.0.dist-info/LICENSE
uniqcharstest3-1.0.dist-info/METADATA
uniqcharstest3-1.0.dist-info/WHEEL
uniqcharstest3-1.0.dist-info/entry_points.txt
uniqcharstest3-1.0.dist-info/top_level.txt
uniqcharstest3-1.0.dist-info/RECORD
